README.md
setup.cfg
setup.py
scraptools/__init__.py
scraptools/scraptools.py
scraptools.egg-info/PKG-INFO
scraptools.egg-info/SOURCES.txt
scraptools.egg-info/dependency_links.txt
scraptools.egg-info/requires.txt
scraptools.egg-info/top_level.txt