Metadata-Version: 2.1
Name: scraptools
Version: 0.0.3
Summary: A small PDF SCRAP
Home-page: https://github.com/pypa/sampleproject
Author: Milap
Author-email: mplabdev@gmail.com
License: UNKNOWN
Platform: UNKNOWN
Classifier: Programming Language :: Python :: 3.7
Classifier: License :: OSI Approved :: MIT License
Classifier: Operating System :: OS Independent
Requires-Python: >=3.7
